{"Location":"US","Interstitial":[0,24,25,59,34,58,54,22,26,57,27,21,28,56,29,35,30,20,31,44,9,32,37,43,8,39,51,19,7,33,68,18,1,67,17,50,6,16,40,49,36,5,42,41,15,66,14,48,4,47,13,65,3,12,46,64,2,11,45,63,55],"iEcpm":[117.464,13.688,0.6,1.25,2.5,5,9,16,25,30,-1,0.5,1,2,3,4.5,7,10,14,20,35,45,60,-1,117.464,117.464,58.732,49.335,44.636,39.938,36.414,31.715,25.842,15.27,76.352,37.588,5.873,25.646,-1,24.52,7,4.918,5,25,30,0.5,1,2,3,7,10,20,-1,-1,60,0.3,40,50,75,90,-1,-1,-1,0.4,0.7,1.5,4,12,15,-1],"Banner":[50,40,41,25,24,0,42,34,37,48,47,35,65,46,64,1,45,63,55,23,36,62,10],"bEcpm":[5.977,0.608,-1,-1,-1,-1,-1,-1,-1,-1,0.15,-1,-1,-1,-1,-1,-1,-1,-1,-1,-1,-1,-1,0.3,5.977,5.977,-1,-1,-1,-1,-1,-1,-1,-1,3.885,1.913,0.299,3.655,-1,-1,7,7,5,-1,-1,0.5,1,2,3,-1,10,-1,-1,-1,-1,0.3,-1,-1,-1,-1,-1,-1,0.2,0.4,0.7,1.5,-1,-1,-1,-1],"Rewarded":[0,1,9,8,7,6,39,40,5,4,3,2],"rEcpm":[76.573,33.574,0.6,1.25,2.5,5,9,16,25,30,-1,-1,-1,-1,-1,-1,-1,-1,-1,-1,-1,-1,-1,-1,-1,-1,-1,-1,-1,-1,-1,-1,-1,-1,-1,-1,-1,-1,-1,7,7,-1,-1,-1,-1,-1,-1,-1,-1,-1,-1,-1,-1,-1,-1,-1,-1,-1,-1,-1,-1,-1,-1,-1,-1,-1,-1,-1,-1,-1],"priority":[],"admob_app_id":"ca-app-pub-5636049984270410~4216589445","admob_app_open_ad":"","applovin_app_id":"UCIc5ZGtBpQ1CInAFK83XMtqltdWynpJxhuS04r8kPawa6Dr3AGIy5sB5XrEA2s56HeS28712r4eiGa5TG8e5J","allow_endless":1,"providers":[{"net":"AdColony","label":"x5.00","settings":"{\"inter_rtb\": \"vzf173a398d8d0494595\",\"appId\": \"appeff3587752384e00a0\",\"banner_rtb\": \"vz66e752a95bcd4e7c9e\",\"reward_rtb\": \"vz6411f36cd7894819a3\"}"},{"net":"MAX","label":"Default","settings":"{\"inter_rtb\": \"95b4d8cfbe3c36ee\",\"banner_rtb\": \"8d98a642a86e51b5\",\"reward_rtb\": \"98553054046b3264\"}"},{"net":"Vungle","label":"00.60","settings":"{\"ApplicationID\": \"61713ec385c2234891413667\",\"inter_PlacementID\": \"I_00_60-9731302\",\"reward_PlacementID\": \"V_00_60-0375862\"}"},{"net":"Vungle","label":"01.25","settings":"{\"ApplicationID\": \"61713ec385c2234891413667\",\"inter_PlacementID\": \"I_01_25-3788738\",\"reward_PlacementID\": \"V_01_25-9232775\"}"},{"net":"Vungle","label":"02.50","settings":"{\"ApplicationID\": \"61713ec385c2234891413667\",\"inter_PlacementID\": \"I_02_50-1456095\",\"reward_PlacementID\": \"V_02_50-6837437\"}"},{"net":"Vungle","label":"05.00","settings":"{\"ApplicationID\": \"61713ec385c2234891413667\",\"inter_PlacementID\": \"I_05_00-6314882\",\"reward_PlacementID\": \"V_05_00-8625827\"}"},{"net":"Vungle","label":"09.00","settings":"{\"ApplicationID\": \"61713ec385c2234891413667\",\"inter_PlacementID\": \"I_09_00-7177748\",\"reward_PlacementID\": \"V_09_00-0536595\"}"},{"net":"Vungle","label":"16.00","settings":"{\"ApplicationID\": \"61713ec385c2234891413667\",\"inter_PlacementID\": \"I_16_00-4097688\",\"reward_PlacementID\": \"V_16_00-4326350\"}"},{"net":"Vungle","label":"25.00","settings":"{\"ApplicationID\": \"61713ec385c2234891413667\",\"inter_PlacementID\": \"I_25_00-9838598\",\"reward_PlacementID\": \"V_25_00-4749624\"}"},{"net":"Vungle","label":"30.00","settings":"{\"ApplicationID\": \"61713ec385c2234891413667\",\"inter_PlacementID\": \"I_30_00-0020533\",\"reward_PlacementID\": \"V_30_00-1780397\"}"},{"net":"Vungle","label":"00.15","settings":"{\"ApplicationID\": \"61713ec385c2234891413667\",\"banner_PlacementID\": \"B_00_15-0161147\"}"},{"net":"Unity","label":"00.50","settings":"{\"GameID\": \"4411819\",\"inter_PlacementID\": \"i_0_5\"}"},{"net":"Unity","label":"01.00","settings":"{\"GameID\": \"4411819\",\"inter_PlacementID\": \"i_1_0\"}"},{"net":"Unity","label":"02.00","settings":"{\"GameID\": \"4411819\",\"inter_PlacementID\": \"i_2_0\"}"},{"net":"Unity","label":"03.00","settings":"{\"GameID\": \"4411819\",\"inter_PlacementID\": \"i_3_0\"}"},{"net":"Unity","label":"04.50","settings":"{\"GameID\": \"4411819\",\"inter_PlacementID\": \"i_4_5\"}"},{"net":"Unity","label":"07.00","settings":"{\"GameID\": \"4411819\",\"inter_PlacementID\": \"i_7_0\"}"},{"net":"Unity","label":"10.00","settings":"{\"GameID\": \"4411819\",\"inter_PlacementID\": \"i_10\"}"},{"net":"Unity","label":"14.00","settings":"{\"GameID\": \"4411819\",\"inter_PlacementID\": \"i_14\"}"},{"net":"Unity","label":"20.00","settings":"{\"GameID\": \"4411819\",\"inter_PlacementID\": \"i_20\"}"},{"net":"Unity","label":"35.00","settings":"{\"GameID\": \"4411819\",\"inter_PlacementID\": \"i_35\"}"},{"net":"Unity","label":"45.00","settings":"{\"GameID\": \"4411819\",\"inter_PlacementID\": \"i_45\"}"},{"net":"Unity","label":"60.00","settings":"{\"GameID\": \"4411819\",\"inter_PlacementID\": \"i_60\"}"},{"net":"Unity","label":"00.30","settings":"{\"GameID\": \"4411819\",\"banner_PlacementID\": \"banner\"}"},{"net":"InMobi","label":"x5.00","settings":"{\"inter_rtb\": \"1634857097563\",\"AccountID\": \"54f9486bbc4c42a4af3404023494c3aa\",\"banner_rtb\": \"1635182159838\"}"},{"net":"Mintegral","label":"x5.00","settings":"{\"appId\": \"152690\",\"apiKey\": \"702a2f322dd9bc99d0e6cdfd9d026115\",\"inter_placement\": \"344144\",\"inter_unit\": \"1572033\",\"banner_placement\": \"344143\",\"banner_unit\": \"1572032\"}"},{"net":"IronSource","label":"x2.50","settings":"{\"inter_Id\": \"6223081\",\"appId\": \"118ddb3cd\"}"},{"net":"IronSource","label":"x2.10","settings":"{\"inter_Id\": \"6223079\",\"appId\": \"118ddb3cd\"}"},{"net":"IronSource","label":"x1.90","settings":"{\"inter_Id\": \"6223077\",\"appId\": \"118ddb3cd\"}"},{"net":"IronSource","label":"x1.70","settings":"{\"inter_Id\": \"6223075\",\"appId\": \"118ddb3cd\"}"},{"net":"IronSource","label":"x1.55","settings":"{\"inter_Id\": \"6223073\",\"appId\": \"118ddb3cd\"}"},{"net":"IronSource","label":"x1.35","settings":"{\"inter_Id\": \"6223071\",\"appId\": \"118ddb3cd\"}"},{"net":"IronSource","label":"x1.10","settings":"{\"inter_Id\": \"6223069\",\"appId\": \"118ddb3cd\"}"},{"net":"IronSource","label":"x0.65","settings":"{\"inter_Id\": \"6223067\",\"appId\": \"118ddb3cd\"}"},{"net":"AdMob","label":"x3.25","settings":"{\"inter_AdUnit\": \"ca-app-pub-5636049984270410/4678612112\",\"banner_AdUnit\": \"ca-app-pub-5636049984270410/7294178927\"}"},{"net":"AdMob","label":"x1.60","settings":"{\"inter_AdUnit\": \"ca-app-pub-5636049984270410/2738527251\",\"banner_AdUnit\": \"ca-app-pub-5636049984270410/8607260594\"}"},{"net":"AdMob","label":"x0.25","settings":"{\"inter_AdUnit\": \"ca-app-pub-5636049984270410/5981097251\",\"banner_AdUnit\": \"ca-app-pub-5636049984270410/2903507777\"}"},{"net":"Facebook","label":"Default","settings":"{\"mediation\": \"max\",\"inter_PlacementID\": \"694207268518152_694208781851334\",\"banner_PlacementID\": \"694207268518152_694208621851350\"}"},{"net":"myTarget","label":"x5.00","settings":"{\"inter_rtb\": \"1054601\",\"appId\": \"1181946\",\"banner_rtb\": \"1054598\",\"reward_rtb\": \"1054604\"}"},{"net":"Tapjoy","label":"Default","settings":"{\"appId\": \"JERyVxlkTiOnTIbGENCjuQECJ1t54TNECgQfuUNsKkbwdGp1eco1refrlK45\",\"mediation\": \"max\",\"inter_rtb\": \"a.i.1153\",\"reward_rtb\": \"a.v.1153\"}"},{"net":"Pangle","label":"Default","settings":"{\"inter_rtb\": \"980159073\",\"AccountID\": \"86231\",\"AppID\": \"8043329\",\"mediation\": \"max\",\"banner_rtb\": \"980159072\",\"reward_rtb\": \"980159074\"}"},{"net":"Kidoz","label":"Default","settings":"{\"AppID\": \"11645\",\"Token\": \"8mvGy08EWJtoUH6CtGjPFUlM2ELDCc1X\"}"},{"net":"AppLovin","label":"05.00","settings":"{\"inter_zoneID\": \"73a7c1b859fe4590\",\"banner_zoneID\": \"f64cd22e39eb7540\",\"reward_zoneID\": \"a35be980f84fb735\"}"},{"net":"AppLovin","label":"25.00","settings":"{\"inter_zoneID\": \"6bb26036770db89d\",\"reward_zoneID\": \"b46609925f4bfbcf\"}"},{"net":"AppLovin","label":"30.00","settings":"{\"inter_zoneID\": \"22e34f6be3bb8eec\",\"reward_zoneID\": \"e96368e8b2065578\"}"},{"net":"AppLovin","label":"00.50","settings":"{\"inter_zoneID\": \"87b3a2fb36ee6202\",\"banner_zoneID\": \"d15a71a688ed16d1\",\"reward_zoneID\": \"6bc5d1da4a0b9910\"}"},{"net":"AppLovin","label":"01.00","settings":"{\"inter_zoneID\": \"617f40bd8224e777\",\"banner_zoneID\": \"493c87fdabf05c94\",\"reward_zoneID\": \"5c8b46dca33216e6\"}"},{"net":"AppLovin","label":"02.00","settings":"{\"inter_zoneID\": \"e9f4b100f7309a96\",\"banner_zoneID\": \"de27c2bdb7b99eba\",\"reward_zoneID\": \"5997573ad53ba3cd\"}"},{"net":"AppLovin","label":"03.00","settings":"{\"inter_zoneID\": \"74e016c8721679d2\",\"banner_zoneID\": \"9ab88789d0a33323\",\"reward_zoneID\": \"b69b4a5a6c72a943\"}"},{"net":"AppLovin","label":"07.00","settings":"{\"inter_zoneID\": \"32c88b06aa7d07c0\",\"reward_zoneID\": \"5ed4032273942a8d\"}"},{"net":"AppLovin","label":"10.00","settings":"{\"inter_zoneID\": \"e43eebb7f30a7988\",\"banner_zoneID\": \"766a3ceefe9831a3\",\"reward_zoneID\": \"e1b69959fda3906d\"}"},{"net":"AppLovin","label":"20.00","settings":"{\"inter_zoneID\": \"2d988b48dc35f5e8\",\"reward_zoneID\": \"4211dcd8b4db1c30\"}"},{"net":"AppLovin","label":"35.00","settings":"{\"reward_zoneID\": \"2de5dd1f80daafe4\"}"},{"net":"AppLovin","label":"45.00","settings":"{\"reward_zoneID\": \"e1be09327dfbfed1\"}"},{"net":"AppLovin","label":"60.00","settings":"{\"inter_zoneID\": \"ebf8c765f7cfc977\",\"reward_zoneID\": \"182da2e05b8dd8ee\"}"},{"net":"AppLovin","label":"00.30","settings":"{\"inter_zoneID\": \"da58d444fc242b83\",\"banner_zoneID\": \"f0ab4eed0ae5e147\",\"reward_zoneID\": \"47e339610b38d229\"}"},{"net":"AppLovin","label":"40.00","settings":"{\"inter_zoneID\": \"af1ff4dd87056293\",\"reward_zoneID\": \"5b8c60a59d136cbd\"}"},{"net":"AppLovin","label":"50.00","settings":"{\"inter_zoneID\": \"6c9da28a185a809c\",\"reward_zoneID\": \"892bd49cd724b418\"}"},{"net":"AppLovin","label":"75.00","settings":"{\"inter_zoneID\": \"ef678e0dd1c23b84\"}"},{"net":"AppLovin","label":"90.00","settings":"{\"inter_zoneID\": \"9290d4e0e03374e1\"}"},{"net":"AppLovin","label":"70.00","settings":"{\"reward_zoneID\": \"9c381d7995ef3e90\"}"},{"net":"AppLovin","label":"80.00","settings":"{\"reward_zoneID\": \"39a81dfbf7d880b1\"}"},{"net":"AppLovin","label":"00.20","settings":"{\"banner_zoneID\": \"e4f5a71feca7a38c\"}"},{"net":"AppLovin","label":"00.40","settings":"{\"inter_zoneID\": \"9b4d078eb36be77f\",\"banner_zoneID\": \"d152d539689c244a\"}"},{"net":"AppLovin","label":"00.70","settings":"{\"inter_zoneID\": \"acb8b8e0b7f2cf4c\",\"banner_zoneID\": \"8ca996e9e88579a7\"}"},{"net":"AppLovin","label":"01.50","settings":"{\"inter_zoneID\": \"9a9cdbb0e13a54f7\",\"banner_zoneID\": \"f04547ada0d77cff\",\"reward_zoneID\": \"54e820bdcf4f3b6d\"}"},{"net":"AppLovin","label":"04.00","settings":"{\"inter_zoneID\": \"c63bda994b8986b6\",\"reward_zoneID\": \"7e4be1aba0309fe2\"}"},{"net":"AppLovin","label":"12.00","settings":"{\"inter_zoneID\": \"913452e664c71d77\",\"reward_zoneID\": \"043ac173bc8f0ef9\"}"},{"net":"AppLovin","label":"15.00","settings":"{\"inter_zoneID\": \"5344b4c8b820bc3b\",\"reward_zoneID\": \"e37a305f447d9e4c\"}"},{"net":"AppLovin","label":"08.00","settings":"{\"reward_zoneID\": \"2be0200bcb50223b\"}"}],"setupPattern":"1110110011101010010010011"}